tracerite/__init__.py
tracerite/chain_analysis.py
tracerite/fastapi.py
tracerite/html.py
tracerite/inspector.py
tracerite/logging.py
tracerite/notebook.py
tracerite/script.js
tracerite/style.css
tracerite/syntaxerror.py
tracerite/trace.py
tracerite/trace_cpy.py
tracerite/tty.py
tracerite-2.3.0.dist-info/METADATA
tracerite-2.3.0.dist-info/WHEEL
tracerite-2.3.0.dist-info/RECORD
