Metadata-Version: 2.4
Name: tracerite
Version: 2.3.0
Summary: Human-readable HTML tracebacks for Python exceptions
Project-URL: Homepage, https://github.com/sanic-org/tracerite
Project-URL: Repository, https://github.com/sanic-org/tracerite
Project-URL: Issues, https://github.com/sanic-org/tracerite/issues
Author-email: Sanic Community <tronic@noreply.users.github.com>
License: Public Domain
Classifier: Development Status :: 5 - Production/Stable
Classifier: Intended Audience :: Developers
Classifier: License :: OSI Approved :: MIT License
Classifier: License :: Public Domain
Classifier: Operating System :: OS Independent
Classifier: Programming Language :: Python :: 3
Classifier: Topic :: Software Development :: Debuggers
Requires-Python: >=3.9
Requires-Dist: html5tagger>=1.2.1
Provides-Extra: nb
Requires-Dist: ipykernel>=6.29.5; extra == 'nb'
Requires-Dist: ipywidgets>=8.1.8; extra == 'nb'
Requires-Dist: jupyter-client>=8.6.3; extra == 'nb'
Requires-Dist: jupyter>=1.1.1; extra == 'nb'
Requires-Dist: jupyterlab>=4.3.8; extra == 'nb'
Requires-Dist: notebook>=7.3.3; extra == 'nb'
